[
  {
    "id": "vol2_test01_part6_raw",
    "volume": 2,
    "test": 1,
    "part": 6,
    "raw_text": "PART 6\nDirections: Read the texts that follow. A word, phrase, or sentence is missing in parts of each text. \nFour answer choices for each question are given below the text. Select the best answer to complete the \ntext. Then mark the letter (A), (B), (C), or (D) on your answer sheet.\nQuestions 131-134 refer to the following notice.\nLakeview Railway Onboard Bicycle Policy\nWould you like to use your bicycle to explore the Lakeview Corridor Scenic Area? Our trains have\nthe------- you need to safely transport your bike. When booking your ticket, just remember that\n131.\nreservations------- for both you and your bicycle. Reserve your bicycle spot -------. There are a\n11 Uwi.\nlimited number of storage racks on each train. You are responsible for stowing your bike securely.\n-------. Lakeview Railway does not take responsibility for bicycles lost or damaged aboard our\n134.\ntrains.\n131. (A) stock\n(B) equipment\n(C) property\n(D) revenue\n132. (A) require\n(B) requiring\n(C) are required\n(D) were required\n133. (A) early\n(B) again\n(C) more\n(D) instead\n134. (A) Folding bicycles have become more\ncommon.\n(B) Additional service fees may apply.\n(C) You can obtain route maps at most\nstations.\n(D) You must also supply your own bike\nlock.\n\n\n\nQuestions 135-138 refer to the following letter.\nCorelli’s Bakery\n15 Middlemass Street\nYoungstown, Ohio 44515\nDear Valued Customer:\nFor the last three years we have charged the same wholesale prices for our baked goods, \nincluding cakes, pies, cookies, and brownies. We regret that sharply rising prices for our raw\ningredients, such as sugar and fruit, have forced us to raise our prices by 5 percent -------\n135.\nAugust 1. We have made every attempt to avoid this price increase. -------, we refuse to\n136.\ncompromise on the quality of our products. Using the best ingredients available will allow us to\nprovide the delicious desserts your restaurant guests have come to expect.------- .\n137 *\nWe appreciate your ------- and look forward to continuing to serve you.\n138.\nSincerely,\nTony Corelli, Owner\n135. (A) actual\n(B) future\n(C) practical\n(D) effective\n136. (A) Similarly\n(B) Therefore\n(C) However\n(D) Accordingly\n138. (A) supportive\n(B) support\n(C) supporter\n(D) supports\n137. \n(A) We believe you will see that our \nproducts are still a great value.\n(B) Our efforts to stay profitable have not\nbeen successful.\n(C) We hope our competitors will raise\ntheir prices too.\n(D) Our products are healthier than\ntraditional baked goods.\n\nQuestions 139-142 refer to the following e-mail.\nTo: Noora Abadi\nFrom: Alexis Palmer\nSubject: Informational interview\nDate: 4 February\nDear Ms. Abadi:\nThank you for taking the time to meet with me yesterday about careers in the aerospace industry.\nYour\n139.\nwere helpful and have inspired me to seek additional work experience in the field\nbefore I apply to graduate school.\nI will consult the Web sites you recommended for job opportunities. As you also suggested, I will\n-------a membership in the Eastern Aeronautics Professional Association. -------. I appreciate the \n140.-------141.\ninformation you shared about the organization’s conference at the end of the month.\nThank you again for your ------- assistance.\nSincerely,\nAlexis Palmer\n139.\n(A) insights\n142. (A) generosity\n(B) surveys\n(B) generous\n(C) improvements\n(C) generously\n(D) revisions\n(D) generousness\n140.\n(A) resolve\n(B) predict\n(C) consider\n(D) advertise\n141.\n(A) I look forward to networking with other\nprofessionals in the field.\n(B) My membership will expire at the end\nof the year.\n(C) I will be giving a presentation at the\nconference.\n(D) I would like to apply for the position\nsoon.\n\n\n\nQuestions 143-146 refer to the following letter.\n15 October\nGPO Box 985\nCANBERRA ACT 6512\nDear Ms. Wilson,\nOn behalf of the Australia Wildlife Park Association, thank you for your donation of 40 AUD to our\nnational park. -------. Individual contributions have helped it stay open to visitors for more than 50 \nI\nyears. Our goal is to keep the park system running effectively for future-------to enjoy.\n144.\nEnclosed please find a copy of our brochure, which lists various programmes\n------- to benefit\n145.\nboth park visitors and our wildlife habitats. Please consider --—— one of these programmes in the\n146.\nfuture. The money would be used wisely and would be deeply appreciated.\nSincerely,\nAkosua Masika, Membership Chair\n143. (A) The association grants scholarships\nfor those studying zoology.\n(B) Supporters like you help preserve the\npark for public use.\n(C) We hope you enjoyed your visit to the\npark today.\n(D) Interested parties can volunteer to\nclean wildlife habitats.\n144. (A) generations\n(B) lifestyles\n(C) committees\n(D) planners\n145. (A) designer\n(B) designs\n(C) designing\n(D) designed\n146. (A) researching\n(B) organizing\n(C) leading\n(D) funding"
  },
  {
    "id": "vol2_test02_part6_raw",
    "volume": 2,
    "test": 2,
    "part": 6,
    "raw_text": "PART 6\nDirections: Read the texts that follow. A word, phrase, or sentence is missing in parts of each text. \nFour answer choices for each question are given below the text. Select the best answer to complete \nthe text. Then mark the letter (A), (B), (C), or (D) on your answer sheet.\nQuestions 131-134 refer to the following e-mail.\nTo: Bai Chang <bchang@lexrg.com>\nFrom: customerservice@sprtech.com\nDate: September 28\nSubject: Order 255646\nDear Ms. Chang:\nThank you for your purchase on September 27. Your package has shipped and is due to arrive on\nOctober 1. -------. Simply visit www.sprtech.com/shipping/status, enter your order number, and\n10 I«\npress “Search.”\nWhen you receive your package, we ------- you to take a short survey at www.sprtech.com/survey. \nI\nIt is through customer feedback that we are ------- to monitor our level of service. Upon \nI 00a\n------- of the survey, you will receive a 10% discount toward your next order.\n134.\nSprtech.com Customer Service\n131. (A) You will receive a full refund.\n(B) A replacement is on back order.\n(C) Tracking your order is easy.\n(D) We will answer your question soon.\n133. (A) able\n(B) skillful\n(C) suitable\n(D) equal\n132. (A) invited\n(B) invite\n(C) were inviting\n(D) have invited\n134. (A) publication\n(B) production\n(C) introduction\n(D) completion\n\nT\nE\nW\nT\n \n\n\n\nQuestions 135-138 refer to the following information.\nConference Room 120 can be booked for meetings and conference calls. First, make a\nreservation request online at www.gzpoffice.com/confroom. When your request -------, the system \nautomatically checks for availability. Your request will be accepted if no other event is scheduled at \nthat time. The system will then immediately send you an e-mail message to ------- your reservation. \n136.\nHowever, if another meeting is scheduled that conflicts with yours, you will be notified that the\nrequest has been declined.------- . It is therefore ------- that you schedule your event well ahead of\ntime. This way, if a given time slot is already reserved, you will be able to reschedule your meeting.\n135. (A) is received\n(B) receiving\n(C) to receive\n(D) received\n138. (A) fortunate\n(B) advisable\n(C) previous\n(D) flexible\n136. (A) move\n(B) cancel\n(C) change\n(D) confirm\n137. (A) Thank you for accepting our invitation to\nthe event.\n(B) Please prepare discussion points before\nthe meeting.\n(C) Note that reservations are on a\nfirst-come, first-served basis.\n(D) The time of the next meeting will be\nannounced in due course.\n\nQuestions 139-142 refer to the following e-mail.\nFrom: Karel Authier <k.authier@codetouchmag.com>\nTo: Honorato Quinones <quinones@voyacon.com.es>\nDate: Tuesday, July 18 11:04 A.M.\nSubject: Voyacon Feature\nDear Mr. Quinones:\nI am delighted to inform you that Voyacon has been selected as one of this year's Code Touch\nMagazine's Top 25 Emerging Technology Firms. We will be ------- your company in our September\n139.\nissue. This is considered a great honor by our readers, as our list includes only------- that advance\n140.\nthe industry in significant ways.\nAs Voyacon's founder, could you e-mail us a digital photograph of yourself to use in the article?\n-------. We would need to receive it ------- August 5. Otherwise, we will use a public-domain photo. \n141. \n142.\nThanks for your help, and congratulations.\nSincerely,\nKarel Authier\nEditor-in-Chief\n139. (A) profile\n(B) profiling\n(C) profiles\n(D) profiled\n140. (A) publications\n(B) machines\n(C) techniques\n(D) enterprises\n141. (A) Hundreds of companies were initially\nconsidered.\n(B) We will forward several copies as soon\nas possible.\n(C) This is the fifth year we will be\npublishing this list.\n(D) It should be a high-resolution, full-color\nimage.\n142. (A) by\n(B) at\n(C) within\n(D) among\n\n\n\nQuestions 143-146 refer to the following memo.\nTo: All Employees\nFrom: Carmen Phelps, Central City Museum Director\nRe: Special Exhibitions Curator\nDate: November 15\nTo All Staff,\nPlease note that an advertisement will be placed in this Wednesday's newspaper regarding a\nnew position at the Central City Museum. After the ------- of Bloom Outside the Box, our recent \nI ■\nexhibition showcasing the artwork of local sculptor Leanne Bloom, the museum board has \ndecided to allocate a new position dedicated to creating new quarterly exhibitions. The position\ntitle is Special Exhibitions Curator. The successful applicant ------- work on January 2.\n144.\n-------■ Proven knowledqe of local and regional artists is preferred. ------- museum staff are\n145.-------u \n146.\nencouraged to apply. Please contact Liliana Wells at extension 449 with questions.\nThank you.\nCarmen\n143. (A) popularity\n(B) winner\n(C) goal\n(D) awareness\n144. (A) started\n(B) will start\n(C) has started\n(D) was starting\n145. (A) Board nominations close at the end of\nthe day on Friday.\n(B) Critic Tony Watanabe gave the\nexhibition a five-star review.\n(C) The position requires extensive\nexperience.\n(D) We look forward to hosting this event.\n146. (A) Expressed\n(B) Observed\n(C) Depended\n(D) Qualified"
  },
  {
    "id": "vol2_test03_part6_raw",
    "volume": 2,
    "test": 3,
    "part": 6,
    "raw_text": "PART 6\nDirections: Read the texts that follow. A word, phrase, or sentence is missing in parts of each text. \nFour answer choices for each question are given below the text. Select the best answer to complete \nthe text. Then mark the letter (A), (B), (C), or (D) on your answer sheet.\nQuestions 131-134 refer to the following advertisement.\nPhiladelphia's PH 11-TV invites you to download our new traffic app for your mobile device. The\ntraffic app today, ------- tune in to our live broadcast beginning at 5:00 a.m. and 4:00 p.m. daily. \nI\napp ------- the station's traffic coverage. Use it to get traffic news if you are away 斤om your \nI V I ■\ntelevision and are unable to watch our traffic reports.-------. Plus, you can program your daily\n132.\ncommute into the app to receive personalized alerts ------- on your mobile device when any \nI OOa\ntraffic-related event occurs along your route. Avoid traffic delays by downloading the PH 11-TV\n131. (A) displaces\n(B) observes\n(C) commands\n(D) supplements\n133. (A) direction\n(B) directly\n(C) directing\n(D) directs\n132. (A) Our city is substantial in size.\n(B) Text messages are subject to service\nfees.\n(C) We send our newscasters to all areas\nof the city.\n(D) The app features 什eq니ent updates.\n134. (A) or\n(B) well\n(C) quick\n(D) only\n\n\n\nQuestions 135-138 refer to the following Web page.\nhttp://www.midwestartisanalcheeseguild.org\nThe Midwest Artisanal Cheese Guild (MACG) organizes trade shows and conducts educational\naround the world.\nThe MACG puts on the region’s largest cheese-maker exposition, held each year in April. The\n-------. His aged Cheddar cheese received a winning score of 98.7 out of 100. \n138.\n138. (A) speaker\n135. (A) is advancing\n(B) to advance\n(C) has advanced\n(D) will advance\n(B) expert\n(C) judge\n(D) champion\n136. (A) these\n(B) each\n(C) when\n(D) instead\n137. (A) Local firm Bromatel demonstrates the\nlatest in cheese-making technology.\n(B) Next year some new conference\nactivities are planned.\n(C) Cheese makers from around the\ncountry compete.\n(D) Hotel reservations can be made on our\nWeb site.\n\nQuestions 139-142 refer to the following information.\nMost of the ------- to Zien Travel Quarterly are professional writers with whom we have an \nI oy.\nongoing relationship. -，we always like to encourage and support new talent. We try to \ninclude at least one article per issue from a new writer, but with just four issues a year, the \nopportunities for publication are quite limited.\nBefore submitting an idea for publication, please read the guidelines at\nwww.zientravel.com/writers, as they outline our specific areas of interest in detail.\nNote that we aim to respond to all correspondence in a timely manner, but there may be times\nwhen we are slow to respond. For this reason, we ask that you please be\n142.\n139. (A) contributes \n142.\n(B) contribution\n(C) contributing\n(D) contributors\n140. (A) With that said\n(B) For instance\n(C) In other words\n(D) In that case\n141. (A) There are dozens of ways to improve one's\nwriting skills.\n(B) That is why an editorial calendar is so\nimportant to our publication.\n(C) This will increase the likelihood of your\nproposal being accepted.\n(D) While this story is excellent, it does not meet\nour needs at this time.\n(A) patient\n(B) secondary\n(C) cautious\n(D) precise\n\n\n\nQuestions 143-146 refer to the following e-mail.\nTo: bgosnell@bvb.org\nFrom: sluu@luumarketing.com\nSubject: Online marketing research\nDate: April 3\nDear Mr. Gosnell,\nBelow are some preliminary conclusions and recommendations based on our analysis of the\ndesign of the Brookside Visitors Bureau Web site.\nFirst, the site is not as ------- as it should be. We recommend updating its appearance and adding \n143.\ninformation that meets the demands of today's tourists. Note also that your organization's logo is\nnot used consistently------- your Web site.\n144.\nYou should also consider supplementing the imagery used to promote the city. -------. We \nI ■\ntherefore recommend uploading some professionally made videos featuring the various\nattractions Brookside has to offer.-------, we suggest adding a page to the Web site that allows\n146.\nresidents and visitors to upload their own photos and videos of city attractions.\nPlease contact me at your earliest convenience to discuss the next steps.\nBest regards,\nShelly Luu\nLuu Marketing\n143. (A) effectiveness\n(B) effectively\n(C) effective\n(D) effecting\n144. (A) upon\n(B) toward\n(C) among\n(D) throughout\n145. (A) No photos can be used without my\nwritten authorization.\n(B) A display of photos is not enough to\nattract prospective visitors.\n(C) A systematic way of filing photos is\nessential for easy retrieval.\n(D) Photos that were not in the proper\nformat have been rejected.\n146. (A) So that\n(B) In addition\n(C) To clarify\n(D) After all"
  },
  {
    "id": "vol2_test04_part6_raw",
    "volume": 2,
    "test": 4,
    "part": 6,
    "raw_text": "PART 6\nDirections: Read the texts that follow. A word, phrase, or sentence is missing in parts of each text. \nFour answer choices for each question are given below the text. Select the best answer to complete \nthe text. Then mark the letter (A), (B), (C), or (D) on your answer sheet.\nQuestions 131 -134 refer to the following memo.\nFrom: Janine Farber\nTo: Barker Marketing Group employees\nDate: September 25\nSubject: Entryway improvements\nstreamlined and contemporary appearance.\nAs many of you have noticed, the main entrance of our building is in ------- conditi이n. It is in\n131.\ndesperate need of attention. Therefore, beginning at 6 p.m. on Friday, the main entrance-------for\n1 32a\napproximately one month as it is renovated. The changes will give the entryway a more \n133. the main entrance is closed, employees and visitors may use the side entrances to gain\naccess to the building.-------\ny 134.\n131. (A) poor\n(B) stable\n(C) physical\n(D) excellent\n132. (A) close\n(B) was closing\n(C) will be closed\n(D) had been closed\n133. (A) While\n(B) During\n(C) Sometimes\n(D) In the meantime\n134. (A) All ground floor offices will remain \naccessible.\n(B) The construction firm has won several\nawards.\n(C) The building is more than 50 years old.\n(D) The board of directors is discussing the\nproject.\n\n\n\nQuestions 135-138 refer to the following article.\n(May 2)—Automotive-manufacturing company Lybera, Inc., today announced that Harvey Ramirez\nhas been appointed as the new chairperson of its board of directors. He ------- Helen McGavick,\n135.\nwho has resigned in order to pursue a new business venture.\n“We thank Ms. McGavick for her service and wish her success in her 제 endeavors’” said Fen\nWang, Lybera's president and CEO.\nMr. Ramirez has spent ten years as CEO of aerospace-engineering firm Elia Aviation.\n, he held a variety of senior management roles across public and private sectors.\n“Mr. Ramirez's familiarity with sophisticated technology, combined with his leadership experience,\nmakes him well suited to lead our company,\" said Mr. Wang.\n138.\n135. (A) replaces\n(B) was replacing\n(C) has been replaced\n(D) would have replaced\n136. (A) advancing\n(B) future\n(C) certain\n(D) instant\n137. (A) Again\n(B) Consequently\n(C) Previously\n(D) However\n138. (A) These meetings take place on a \nregular basis.\n(B) The product is currently being\ndeveloped.\n(C) We hope to learn more about the\nposition.\n(D) We look forward to his guidance.\n\nQuestions 139-142 refer to the following letter.\n25 February\nDear Ms. Nguyen,\nWe appreciate your feedback regarding Medusa Airways' flight 859, which was scheduled to\ndepart at 9:35 a.m. on 19 February. We are sorry that this flight -------. We have decided to \ni oy ■\ncompensate you for the -------. We have refunded the unused portion of your ticket, valued at\n$410. Also, we will reimburse the $200 you paid in hotel charges resulting-------  the disruption.\n141.\n. Please allow up to five business days for the transactions to process.\nSincerely,\nYeeking Lai\nCustomer Relations Manager\n139. (A) was canceled\n(B) will be canceled\n(C) had to cancel\n(D) is canceling\n140. (A) work\n(B) time\n(C) drawback\n(D) inconvenience\n141. (A) above\n(B) near\n(C) from\n(D) beyond\n142. (A) We hope you have an enjoyable trip.\n(B) Both amounts have been credited to\nyour account.\n(C) Your complaint will soon be reviewed.\n(D) Thank you for your understanding.\n\n\n\nQuestions 143-146 refer to the following e-mail.\nTo: Film crew\nFrom: Sandeep Goswami\nDate: Monday, October 2\nSubject: Barn scene retake\nDear Crew,\nThis is a reminder that on Saturday we will be doing a retake of the advertisement featuring the \nhorses at Willow Stables. Filming with animals can be unpredictable, and last week we were not \nable to get the footage we needed. -------, I would like to begin promptly at 8:00 a.m. so that we \nI 나 0.\ncan film from a number of angles before lunch. As long as everyone is punctual and everything\ngoes well, we should get the footage we need by then.\n144.\nI also want to------- the fact that the set is closed to all who are not absolutely essential to the\n145.\nfilming of the scene. Anyone else will be too much of a -------.\nSandeep Goswami\nMonarda Productions\n143. (A) Otherwise\n(B) In either case\n(C) If possible\n(D) Alternatively\n144. (A) I was impressed by the rehearsal.\n(B) Luckily, it is not noticeable to viewers.\n(C) We will need different equipment.\n(D) However, it may take the full day.\n145. (A) research\n(B) challenge\n(C) avoid\n(D) stress\n146. (A) distraction\n(B) distracting\n(C) distracted\n(D) distract"
  },
  {
    "id": "vol2_test05_part6_raw",
    "volume": 2,
    "test": 5,
    "part": 6,
    "raw_text": "PART 6\nPower Outage Scheduled at City Hall\nOn Friday, April 14, the city hairs electricity is scheduled to be shut down at 7 a.m. and restored at\n6 p.m. The building-------for the day. During the power outage, the emergency lighting system will\n131.\nbe upgraded. , all circuit panels will be replaced to bring them into compliance with current \nI ■\nsafety codes.\n133. exiting city hall offices on Thursday, please disconnect all desktop computers, wireless\nservers, and other computer-related equipment. Furthermore, employees are asked to remove any\npersonal contents from the kitchenette.\n134.\nPlease direct questions or concerns to the director\nof building maintenance.\n131. (A) has closed\n(B) closing\n(C) will close\n(D) was closing\n132. (A) In that case\n(B) Regularly\n(C) Rather than\n(D) Specifically\n133. (A) Inside\n(B) Beyond\n(C) Without\n(D) Before\n134. (A) Any items left behind will be discarded.\n(B) The contents of each refrigerator must\nbe labeled.\n(C) Employees should report to work as\nusual.\n(D) Emergency lighting will allow each\ndepartment to remain operational.\n\nDirections: Read the texts that follow. A word, phrase, or sentence is missing in parts of each text. \nFour answer choices for each question are given below the text. Select the best answer to complete \nthe text. Then mark the letter (A), (B), (C), or (D) on your answer sheet.\nQuestions 131-134 refer to the following notice.\nTEST\n \nw\n\n\nQuestions 135-138 refer to the following e-mail.\nTo: Annette Schreiber <aschreiber@www.aschreiber.net>\nFrom: Herbert Peraino, General Manager <hperaino@partyon.com>\nDate: May 5\nSubject: Private Party\nHello Ms. Schreiber,\nThank you for considering Partyon for your upcoming event. We welcome the opportunity to inform \nyou about the areas we have available.\n-------. Our patio, for instance, can hold up to 15 people. This space is ------- for small\n135. \n136.\nget-togethers. Our lounge area can fit up to 40 people. It is best suited for informal -------. \nI U f ■\nThen there’s our grand dining room, intended for more formal parties. It offers accommodations\nfor up to 60 guests. Moreover, we can ------- design either a lunch or dinner menu for you\n138.\naccording to your specifications.\nIf you have any further questions, please do not hesitate to contact us.\nSincerely,\nHerbert Peraino\n135. (A) We offer different settings depending\non the size of your party.\n(B) We are happy to answer any query\nyou have about available dates.\n(C) We are interested in hearing your\nopinion about our services.\n(D) We offer lunch and dinner catering\noptions for various types of events.\n136. (A) worried\n(B) exact\n(C) ideal\n(D) ultimate\n137. (A) gatherings\n(B) locales\n(C) collections\n(D) methods\n138. (A) easy\n(B) easily\n(C) ease\n(D) easier\n\nQuestions 139-142 refer to the following article.\nTAYLORSVILLE (October 4)—Mayor Bo Crandell of the town of Taylorsville announced plans for a \nbicycle-share program this week. Past efforts to encourage the use of bicycles for transportation\nfailed because there were no convenient areas to park bicycles downtown. Additionally, cyclists\n-------to share narrow streets with cars and trucks, raising safety concerns.\n139.\nWith the new bicycle-share initiative, bicycle stations will be placed ------- at eight locations around\nTaylorsville. One important purpose of the initiative is to ease the limited vehicle parking in the\ndowntown area., I want to encourage local residents to spend more time outdoors and \n141.\nenjoy our beautiful town,\" added the mayor at the end of his remarks. -------.\n139. (A) were forced\n(B) force\n(C) will be forcing\n(D) have forced\n140. (A) strategizing\n(B) strategy\n(C) strategic\n(D) strategically\n141. (A) Otherwise\n(B) Rather\n(C) Moreover\n(D) Similarly\n142. (A) People who use the program have \ncreated Web-site accounts.\n(B) In a recent survey, many respondents\nmentioned a concern for safety.\n(C) Nearby Grandmonfs bicycle-share\nprogram is in its fifth successful year.\n(D) He aims to have the bicycle stations\nready for use as early as next April.\n-4 \nrn \n■니\n\n\n\nQuestions 143-146 refer to the following e-mail.\nTo: All employees\nFrom: Alex Muresianu\nDate: 28 June\nSubject: New employee handbook training\nKlok Financial has recently updated its employee handbook. ------- Although the information \nI\nconcerning benefits and terms of employment remains the same, other important modifications \nhave been made. This version of the handbook includes new policies concerning e-mail privacy,\nInternet use, and use of mobile devices. Our travel guidelines have also been -------. The process\n144.\nfor reimbursement after a trip is now much more efficient.\nAll employees must attend an informational session about the policies. One-hour sessions will be\nacknowledging that they have received, read, and understood the information contained in the \nhandbook and that they accept the terms. Please arrange with your manager ------- one of these\n146.\nsessions.\nAlex Muresianu\n143. (A) Thank you for adhering to the policies.\n145. (A) In summary\n(B) On the other hand\n(C) As a matter of fact\n(D) Immediately afterward\n(B) Our new logo is displayed on the \ncover.\n(C) This is the first change in over ten \nyears.\n(D) Corporate lawyers were hired to write \nit.\n146. (A) to attend\n(B) who attended\n(C) while attending\n(D) in attendance at\n144. (A) revised\n(B) deleted\n(C) discussed\n(D) notified"
  },
  {
    "id": "vol2_test06_part6_raw",
    "volume": 2,
    "test": 6,
    "part": 6,
    "raw_text": "PART 6\nDirections: Read the texts that follow. A word, phrase, or sentence is missing in parts of each text. \nFour answer choices for each question are given below the text. Select the best answer to complete \nthe text. Then mark the letter (A), (B), (C), or (D) on your answer sheet.\nQuestions 131-134 refer to the following article.\nDODOMA (21 May)—Dodoma Gas and Electric (DGE) and Arusha Power (Arupo) have\nannounced today that they ------- into one company. The effective date of the merger is 1 July. The\n131.\nsoon-to-be-------comoanv will ooerate under the new name Tanzania Enerav Solutions. DGE\njoint statement, CEOs Johnathan Gashaza of DGE and Coretha Komba of Arupo assured\n134. (A) We\n(A) have been merging\n(B) will be merging\n(C) have merged\n(D) are merged\n131.\n(B) It\n(C) They\n(D) She\n132. (A) renovated\n(B) informed\n(C) created\n(D) acquired\n133. (A) The financial terms of the agreement\nhave yet to be disclosed.\n(B) The energy sector is vital to Tanzania’s\ndevelopment.\n(C) Both companies have an exceptional\ngrasp of the international financial \nmarket.\n(D) Both companies have an excellent\nreputation in their respective \nindustries.\n\n\n\nQuestions 135-138 refer to the following letter.\n29 August\nAlvin Mangubat\nDirector of Human Resources\nFarsten Products, Ltd.\n549 Castor Boulevard\nWinnipeg MB R3E 2S2\nDear Mr. Mangubat,\nI am writing to apply for the mechanical engineer position advertised on your Web site. I think I\nhave much to offer Farsten Products1 design ------- as an employee.\n135.\n-------. I am currently an engineer at Yount Systems, where I have worked on machine and engine\n136.\ndesigns for the last six years. ------- that, I was employed by Zelenka Industries, where I helped \nI O f ■\ndevelop efficient methods for recycling scrap steel.\nI have enclosed my resume, which ------- more details about my work history and my educational \n138.\nbackground. I look forward to meeting with you to discuss how my skills and experience can\nbenefit Farsten Products.\nSincerely,\nGail Paek\nEncl.\n135. (A) phase\n(B) department\n(C) consultant\n(D) expertise\n137. (A) Regarding\n(B) Following\n(C) Contrary to\n(D) Prior to\n136. (A) Your Web site also listed an internship \nthat would be a great opportunity.\n(B) The job description said that applicants\nshould have an advanced degree.\n(C) My manager replied to your request last\nweek.\n(D) My extensive experience makes me an\nideal fit for your company.\n138. (A) give\n(B) gave\n(C) gives\n(D) is giving\n\nQuestions 139-142 refer to the following e-mail.\nTo: Lathifah Suryani <lsuryani@cmail.com>\nFrom: Jabari Evers <eversj@pems.com>\nDate: May 18\nSubject: Text Messages\nDear Ms. Suryani,\nIn order to------- our patients as effectively and reliably as possible, we are now offering them the\n139.\noption of receiving appointment reminders and other relevant information via our text-messaging\nsystem. You are currently registered to receive our materials via e-mail. -------. If you would like to \nadd text messaging to your mode of communication with us or would like to change your ------- \nfrom e-mail to text messaging, please let us know at your earliest convenience. ------- goal is to \ngive you relevant and useful information about your health and about the products and services\nwe offer in a timely fashion.\nJabari Evers\nCustomer Care Representative\nProfessional Eye Care Management Services\n139. (A) serve\n(B) care\n(C) work\n(D) provide\n140. (A) You have not been in our office\nrecently.\n(B) No action is required if you like your\ncurrent service.\n(C) We have great products you can buy.\n(D) E-mail messages are not available to\nall patients.\n141. (A) prefer\n(B) preferential\n(C) preferred\n(D) preference\n142. (A) Their\n(B) My\n(C) Your\n(D) Our\n\n\n\nQuestions 143-146 refer to the following article.\nTOFTLUND (10 June)_Row after row of electric cars in local parking areas seem to indicate that \nthe city of Toftlund has begun to give up on gasoline-fueled cars. In fact, 20 percent of the cars\non Toftlund city streets are electric, but this number is changing at a pace.\n143.\nTo some extent, this is due to the city’s generous tax ------- offered to electric car drivers.\n144.\nAccording to Anne Rasmussen, president of Toftlund Green Business, more attractive designs\nand longer-lasting batteries have ------- made a difference. Ms. Rasmussen predicts the number\n145.\nof electric cars in Toftlund will more than double in the coming years.-------.\n146.\n143. (A) rapid\n(B) brief\n(C) narrow\n(D) valuable\n144. (A) beneficial\n(B) benefitting\n(C) benefits\n(D) to benefit\n145. (A) just\n(B) over\n(C) very\n(D) also\n146. (A) Moreover, she likes the convenience \nof having recharging stations on \nhighways.\n(B) In fact, she believes that in twenty\nyears only electric cars will be sold \nhere.\n(C) Therefore, she feels that the price of\nelectric cars is too high.\n(D) She notes that the population of\nToftlund has been decreasing \nsteadily."
  },
  {
    "id": "vol2_test07_part6_raw",
    "volume": 2,
    "test": 7,
    "part": 6,
    "raw_text": "PART 6\nDirections: Read the texts that follow. A word, phrase, or sentence is missing in parts of each text. \nFour answer choices for each question are given below the text. Select the best answer to complete \nthe text. Then mark the letter (A), (B), (C), or (D) on your answer sheet.\nQuestions 131-134 refer to the following article.\nTOKYO (2 June)—Toda Entertainment announced this morning that it will be revealing its latest\nvideo game later this week. A preview of the game ------- 3 presentation from the developers will be \nI O I •\nbroadcast on the company’s Web site on Friday at 4:00 p.m. Japan Standard Time. Until now, no\ndetails have been revealed about the game. Many consumers are already that it will be a \nsequel to the company’s popular Todashi Adventure series. The first game in that series, released\ntwo years ago, was a ------- success for the company, selling over 400,000 copies in Japan. ------- \nI Ju.\n131. (A) but\n(B) even though\n(C) how\n(D) as well as\n132. (A) confirming\n(B) speculating\n(C) requesting\n(D) analyzing\n133. (A) remarkable\n(B) remarkably\n(C) remarking\n(D) remark\n134. (A) The company was not able to meet \nthis goal.\n(B) Toda Entertainment will announce its\nnew CEO next week.\n(C) Its worldwide sales were double that\nnumber.\n(D) Consumers can now purchase it for\nthe first time.\n\n\n\nQuestions 135-138 refer to the following letter.\nJuly 11\nDear Mr. Wong:\nIt was good to speak with you today about the opening in the accounts receivable department at\nRiedeberg Realty. -------. My prior experience has prepared me particularly well for this -------.\n135. \n136.\nStrong writing skills, assertiveness, and accuracy -------y- in my last two jobs. I am also able to work \neffectively with coworkers, especially in a fast-paced environment.\nI appreciate the time you took to ------- me. I look forward to hearing from you when you make your\n138.\nfinal hiring decision.\nSincerely,\nJon Troughman\n135. (A) The job seems like an ideal match for\nmy skills and interests.\n(B) The company had an outstanding\nreputation nationally.\n(C) Note that I have applied for a number\nof other jobs as well.\n(D) Please contact me to discuss\nadditional scheduling options.\n136. (A) event\n(B) incident\n(C) position\n(D) exception\n137. (A) all requiring\n(B) had all required\n(C) all requirements\n(D) were all required\n138. (A) train\n(B) recommend\n(C) entertain\n(D) interview\n\nQuestions 139-142 refer to the following Web page.\nProtection & Conservation\nThe Garner Museum of Art (GMA) ensures the preservation of its collection by carefully ------- the \nI oy.\nlighting of its galleries. Certain artifacts—many of which are thousands of years old—are particularly\nsensitive to light.------- ，the museum does not showcase any of its pieces in areas with windows.\n140.\nNor does it keep artwork in areas with certain kinds of -------, potentially harmful bulbs. -------. By\n141. \n142.\ntaking such measures, the GMA hopes that its collection will be enjoyed for generations to come.\n139. (A) monitoring\n(B) acquiring\n(C) performing\n(D) guarding\n140. (A) After all\n(B) For instance\n(C) On the contrary\n(D) For this reason\n141. (A) bright\n(B) brightly\n(C) brighten\n(D) brightness\n142. (A) Therefore, the museum will place \nsome of its older pieces on loan.\n(B) Also, flash photography is not\npermitted.\n(C) Only a few staff members possess\nthese specialized skills.\n(D) Unfortunately, it can be difficult to\ndetermine an object’s age.\n►\n\n\nQuestions 143-146 refer to the following e-mail.\nTo: All Managers\nFrom: Bert Pizarro\nDate: October 10\nSubject: Staff banquet\nDear Managers,\nDecember is quickly approaching, and the Human Resources team is working out the details for \nthis year’s staff banquet. As you know, this event is an opportunity for us to thank our entire \nstaff for their service and to reflect on the past twelve months. In addition, it will provide everyone \nwith the opportunity ------- time with their colleagues in a relaxed social setting.\nWe know that the distance to last year's banquet in Riverdale made it difficult for several employees \nto attend the event. To make it easier for everyone to participate in this celebration, we are looking\nfor a that is closer to our office building.-------.\n145. \nᄇ 146.\nWe plan to send out further details soon.\nKind regards,\nBert Pizarro\nHuman Resources Manager\n143. (A) initial\n(B) annual\n(C) favoring\n(D) hiring\n144. (A) to spend\n(B) having spent\n(C) spending\n(D) will spend\n145. (A) result\n(B) transport\n(C) capacity\n(D) venue\n146. (A) Driving directions are attached.\n(B) We apologize for the confusion.\n(C) Please reply with any suggestions.\n(D) Remember to confirm your\nattendance."
  },
  {
    "id": "vol2_test08_part6_raw",
    "volume": 2,
    "test": 8,
    "part": 6,
    "raw_text": "PART 6\nDirections: Read the texts that follow. A word, phrase, or sentence is missing in parts of each text. \nFour answer choices for each question are given below the text. Select the best answer to complete \nthe text. Then mark the letter (A), (B), (C), or (D) on your answer sheet.\nQuestions 131-134 refer to the following advertisement.\nItaly has so much to offer—museums, gardens, beautiful scenery, and great food. For one low \nprice, the All-ltaly Pass provides access to more than a hundred popular attractions across the\ncountry. The more you ------- it, the better value you will get.\n131.\n-------. Passes must be purchased online before you leave your home country and are activated \n132.\nwhen you visit your first attraction. They will remain ------- for 21 days.\n131. (A) user\n133. (A) open\n(B) using\n(C) use\n(D) used\n(B) valid\n(C) constant\n(D) ordinary\n132. (A) The offer is only available to\n134. (A) besides\nweek.\n(C) The attractions are very crowded in\ninternational visitors.\n(B) Tourists cannot see all the sites in a\n(B) also\n(C) after\n(D) beyond\nthe summer.\n(D) Several companies offer tour guides.\n\n\n\nQuestions 135-138 refer to the following e-mail.\nTo: Weiyi Shan <wshan@strategiccomm.org>\nFrom: Arvin Flores <aflores@floresmanufacturing.com>\nDate: April 5\nSubject: March 28 workshops\nDear Mr. Shan,\nI am writing to share our ------- for the workshops Alana Hughes delivered at our corporate \nI 00.\nheadquarters on March 28. Some employees ------- a concern regarding the usefulness of\n136.\nimprovisation training in a business setting. These same employees participated fully throughout \nthe day and even inquired about the possibility of follow-up sessions. We asked participants to\ncomplete our company’s evaluation form\n137. to better gauge the effectiveness of the workshops.\nResults were mainly positive, with 90 percent of participants stating that their communication skills\nare now stronger. -------. Please let me know if you would like to discuss the workshops in more \n138.\ndetail.\nBest regards,\nArvin Flores\n135. (A) appreciate\n(B) appreciative\n(C) appreciated\n(D) appreciation\n136. (A) express\n(B) are expressing\n(C) were to be expressed\n(D) had expressed\n137. (A) afterward\n(B) often\n(C) since\n(D) instead\n138. (A) The workshop will be rescheduled for \nlater in the week.\n(B) A few participants said they would have\nliked more practice.\n(C) An additional workshop in team building is\noccasionally offered.\n(D) We will provide you with an invoice\nrequesting payment.\n\nQuestions 139-142 refer to the following e-mail.\nTo: Li Cheung <lcheung@broadwayos.com>\nFrom: Travis Juno <tjuno@hiraokaarchitecture.com>\nDate: November 18\nSubject: Monthly order\nDear Mr. Cheung:\nWe need to make an adjustment to Hiraoka Architecture’s ------- order. Fewer of our presenters are \nI oy.\nusing dry-erase whiteboards in their presentations, and as a result, we are using fewer BR1608 \ndry-erase markers. -------: I would like to reduce the number in our order to only twelve of those \nbeginning next month. Please raise the number of GN2280 all-purpose markers to fourteen.\nWe will eventually phase 이Jt the BR1608 markers entirely. However, I ------- you plenty of notice \nbefore then, probably by late next year.\nCan you send a statement with the revised monthly bill? -------.\n\n142.\nBest,\nTravis Juno\nHiraoka Architecture\n139. (A) still\n(B) overdue\n(C) standing\n(D) redundant\n140. (A) Therefore\n(B) Typically\n(C) Similarly\n(D) Nevertheless\n141. (A) give\n(B) have been given\n(C) gave\n(D) will give\n142. (A) We have not yet used up our \ninventory.\n(B) You can find it in your e-mail inbox.\n(C) Our finance department will need it.\n(D) Employees are happy with the\nproduct.\n\n\n\nQuestions 143-146 refer to the following letter.\n13 March\nDennis Carrera\nLejos Plumbing and Heating\nSan Antonio, Texas\nDear Mr. Carrera:\nCongratulations! Mallorca Construction ------- the bid of Lejos Plumbing and Heating to provide \nI 나u，\nenhancements to the County Courthouse. Your workers will have access to the-------on May 5.\n144.\nAs specified by the district building code, Lejos Plumbing and Heating will be responsible for \nsecuring the required permits. The enclosed plan outlines the scope of the project.\n-------, the document lists the other contractors we are partnering with, and it reveals how your \nI\nfirm's work fits into the overall project.\nWe are requesting no significant adjustments to the blueprints and specifications you submitted \nwith your proposal. Please contact my office if you need additional information. -------.\n146.\nSincerely,\nPetra Rojas, Manager\nMallorca Construction Ltd.\nEnclosure\n143. (A) may accept\n(B) would accept\n(C) has accepted\n(D) was accepting\n144. (A) site\n(B) data\n(C) results\n(D) product\n145. (A) However\n(B) In addition\n(C) As a result\n(D) On the other hand\n146. (A) Unfortunately, your bid arrived after \nthe deadline.\n(B) We will inform you of our final decision\nsoon.\n(C) Best wishes again on your recent\nexpansion.\n(D) We will provide it to you promptly."
  },
  {
    "id": "vol2_test09_part6_raw",
    "volume": 2,
    "test": 9,
    "part": 6,
    "raw_text": "PART 6\nDirections: Read the texts that follow. A word, phrase, or sentence is missing in parts of each text. \nFour answer choices for each question are given below the text. Select the best answer to complete \nthe text. Then mark the letter (A), (B), (C), or (D) on your answer sheet.\nQuestions 131-134 refer to the following e-mail.\nTo: Eriford Hotel Staff\nFrom: Seth Park\nSubject: Conserving resources\nDate: 15 March\nTo all housekeeping staff:\nHotel management has decided to implement a new policy ------- the daily laundering of towels.\n131.\nGoing forward, all towels left on the floor by guests will be collected and washed each day, but any\nused towels hung up on hooks or racks will be left in the room for guests to reuse. This policy will\n------- our daily laundry load. , our electricity and power use will be reduced.\nI \nI OOa\nNotices will be posted in each room informing our guests of this policy.------- . The management is\nI\ndeeply committed to conservation.\nThank you,\nSeth Park\nHospitality Manager, Eriford Hotel\n131. (A) regards\n(B) regardless\n(C) regarding\n(D) regarded\n132. (A) minimize\n(B) double\n(C) require\n(D) eliminate\n133. (A) Despite this\n(B) However\n(C) As a result\n(D) Evidently\n134. (A) We would greatly appreciate your \ncooperation with this effort.\n(B) Please inform us if you identify any\nmaintenance needs.\n(C) During this time, please try to limit\nshowers to ten minutes.\n(D) You will be asked to share all of your\nideas at the staff meeting.\n\n\n\nQuestions 135-138 refer to the following notice.\nAttention Travelers:\noffice as soon as possible after arrival. Domestic travelers are asked to report damage within 24 \nhours of reaching their destination, and international travelers must submit a report within five days\nof an incident. -------. Office personnel will review and evaluate all -------w. Be advised that Cloud \n136. \n137.\nExpress Airlines is not responsible for preexisting conditions or broken zippers or buckles related\nto overpacking or ------- wear.\n138.\n135. (A) brings\n137. (A) claims\n(B) brought\n(C) bring\n(D) bringing\n(B) agendas\n(C) passports\n(D) rates\n136. (A) Cloud Express has recently\nexpanded its international routes.\n138. (A) normality\n(B) Cloud Express hires only the most \nqualified employees.\n(B) normal\n(C) normally\n(D) normalize\n(C) The baggage office will be \ntemporarily closed this week.\n(D) Please complete the baggage \ndamage form as instructed.\n\nQuestions 139-142 refer to the following memo.\nTo: Broome Library Staff\nFrom: Ainsley Mason\nRe: Community Rooms\nDate: April 20\nI am pleased to report that construction of our new community rooms will be complete by the end of \nthis month. The four rooms will be ------- from the main lobby.\n139.\nThe new rooms range in occupancy from 10 to 25 people and are intended for meetings and study\ngroups. . Ms. Sundquist will be temporarily responsible for reserving the spaces until the end\nof March.------- ，she will return to her role as Library Information Specialist. An advertisement will\n141.\nbe posted soon for a permanent Community Liaison. This individual will be in charge of\nbookings for the new rooms.\n139. (A) accessible\n(B) assorted\n(C) appropriate\n(D) acceptable\n140. (A) Interviews will be conducted in early\nMay.\n(B) Lynn Sundquist has led many\nmeetings.\n(C) All rooms must be reserved in\nadvance.\n(D) Staff parking spaces will be marked\nclearly.\n141. (A) Nonetheless\n(B) At that time\n(C) Likewise\n(D) In a word\n142. (A) oversee\n(B) oversees\n(C) overseen\n(D) overseeing\n\n\n\nQuestions 143-146 refer to the following e-mail.\nTo: tkhan@smolermanufacturing.co.uk\nFrom: lpreston@emmetestate.co.uk\nDate: 9 March\nSubject: 1161 Coral Lane\nDear Ms. Khan,\nThank you for asking about the 200-square-metre warehouse space at 1161 Coral Lane. I checked \nmy real estate database, and this property has been taken off the market.\nIf you would like to give me an idea of what specifically you are looking for, I-------you in finding\n144.\nsomething else. Just respond to this e-mail with your price range, size needs, preferred area of\ntown, and any other important requirements.-------.\n145.\nIf you wish, you may also sign up for -------. This way you will receive instant e-mail or \n146.\ntext-message notifications whenever new property listings become available.\nBest regards,\nLloyd Preston\nEmmet Estate Agents\n143. (A) briefly\n(B) considerably\n(C) apparently\n(D) primarily\n144. (A) am assisting\n(B) can assist\n(C) have been assisting\n(D) assist\n145. (A) For example, you need approval\nbefore anything is upgraded.\n(B) I will be showing this property to\npotential buyers on Thursday.\n(C) It is an interesting trend in the real\nestate industry.\n(D) Then I will search for commercial\nbuildings that meet these criteria.\n146. (A) alerts\n(B) payments\n(C) activities\n(D) inspections"
  },
  {
    "id": "vol2_test10_part6_raw",
    "volume": 2,
    "test": 10,
    "part": 6,
    "raw_text": "PART 6\nDirections: Read the texts that follow. A word, phrase, or sentence is missing in parts of each text. \nFour answer choices for each question are given below the text. Select the best answer to complete \nthe text. Then mark the letter (A), (B), (C), or (D) on your answer sheet.\nQuestions 131-134 refer to the following notice.\nPro Unis is now hiring for positions in our production, human resources, and accounting\ndepartments. As one of the region’s largest employers, Pro Unis------- workforces with uniforms for\n131.\nover 70 years. Since our founding, Pro Unis has been committed to employee retention and -------. \nI\nWe offer competitive wages, job training, and regular opportunities for promotion. To learn more\nabout -------, visit prounis.com/careers. Interested job-seekers will be directed to fill out an online\n133.\napplication and upload a resume. -------.\n131. (A) outfitted\n(B) will outfit\n(C) is outfitting\n(D) has been outfitting\n133. (A) issues\n(B) events\n(C) openings\n(D) investments\n132. (A) advanced\n(B) an advance\n(C) they advance\n(D) advancement\n134. (A) They must also pass a background \ncheck to be eligible for employment.\n(B) Let Pro Unis design work uniforms for\nyour company.\n(C) You can now follow us on social\nmedia.\n(D) We recently hired a new director of\nhuman resources.\n\nT\nr\nE\nm\nT\n \n\n\n\nQuestions 135-138 refer to the following information.\nWS Dental is pleased to announce that our practice is\n135.\n. Our second office is now open at 242\nUnion Street in Lambton, offering greater ------- for patients living on the north side of the city. Our \n136.\noriginal clinic will continue to operate at 12 Finn Place. Dr. Walbeck and Dr. Steiner are committed\nto providing\n137. care at both locations.\nWS Dental provides a full range of dental services at both offices. They are both open from 8 a.m.\nto 5 p.m., Monday through Friday. -------. Extended evening hours will be considered in the coming\n138.\nseason.\n135. (A) training\n(B) expanding\n(C) calling\n(D) moving\n136. (A) collection\n(B) production\n(C) performance\n(D) convenience\n137. (A) exception\n(B) exceptions\n(C) exceptional\n(D) exceptionally\n138. (A) Our Finn Place office is also open on \nSaturday mornings.\n(B) This area has a rich history and a vibrant\ndowntown.\n(C) The facility is comfortable, clean, and\nbright.\n(D) Once there, take a right onto Mountain\nView Road.\n\nQuestions 139-142 refer to the following e-mail.\nTo: jroux@xmail.com\nFrom: josephbelle@perilleuxrealestate.com\nDate: March 2\nSubject: Your job inquiry\nDear Ms. Roux:\nYour resume ------- to me by a colleague. \nI O 5/.\n140. . We appreciate your interest in Perilleux Real Estate\nand will keep your\n141. on file in case a full-time position opens up in the future.\n-------，would you consider working for us part-time on a special project? Our CEO needs \nadministrative support on an ambitious advertising campaign. The project should last until the end \nof July.\nKindly let me know if this opportunity interests you.\nSincerely,\nJoseph Belle, Vice President\nHuman Resources\n139. (A) to pass on\n(B) will pass on\n(C) is passing on\n(D) was passed on\n140. (A) It was nice to meet you at the\nnetworking event.\n(B) Our firm is now six years old.\n(C) We are happy to have you as part of\n이jr team.\n(D) Unfortunately, we do not have an open\nreceptionist position.\n141. (A) documents\n(B) analysis\n(C) descriptions\n(D) reports\n142. (A) First of all\n(B) As mentioned\n(C) In the meantime\n(D) In order that\n\nT\nE\nW\nr\n \n\n\n\n\nQuestions 143-146 refer to the following article.\nHurst Airlines Improves its Customer Service Offerings\nLOS ANGELES (September 22)—Hurst Airlines has started installing self-check-in kiosks where \npassengers can scan their identification, print their own boarding passes, and tag their own \nluggage to be loaded onto the aircraft. These new - are already in place at two airports in\nCalifornia.------- will soon be available at all airports where Hurst Airlines flies. According to Hurst\n144.\nAirlines CEO Roxana Ghazi, the company aims for all its service areas ------- equipped with\n145.\nkiosks by the end of the summer.\nThe intent of these kiosks is to make the check-in process run more quickly. Said Ms. Ghazi, “We\nhave limited staff, and lines can often be quite long. -------. These new kiosks are expected to\n146.\nsignificantly reduce the amount of time spent in line.”\n143. (A) devices\n(B) positions\n(C) materials\n(D) regulations\n144. (A) It\n(B) She\n(C) They\n(D) Either\n145. (A) to be\n(B) that are\n(C) they were\n(D) having been\n146. (A) Unfortunately, we are changing our \nroutes.\n(B) Passengers should arrive two hours\nbefore a flight.\n(C) We expect to hire more staff soon.\n(D) This is especially true during peak\noperating times."
  }
]